[
    {
        "domain": "17b14bbf",
        "gid": "0f0e83da",
        "name": "p\u00e2te de lasagnes",
        "unit": "ffa29d26"
    },
    {
        "domain": "164a7427",
        "gid": "0a34c760",
        "name": "oignon",
        "unit": "590c07ad"
    },
    {
        "domain": "164a7427",
        "gid": "e452d503",
        "name": "ail",
        "unit": "590c07ad"
    },
    {
        "domain": "164a7427",
        "gid": "128be540",
        "name": "branche de c\u00e9leri",
        "unit": "590c07ad"
    },
    {
        "domain": "164a7427",
        "gid": "21325467",
        "name": "carotte",
        "unit": "590c07ad"
    },
    {
        "domain": "651fbb34",
        "gid": "a8638255",
        "name": "viande de boeuf hach\u00e9e",
        "unit": "ffa29d26"
    },
    {
        "domain": "17b14bbf",
        "gid": "03ea9006",
        "name": "pur\u00e9e de tomate",
        "unit": "ffa29d26"
    },
    {
        "domain": "575e78ac",
        "gid": "9007c83c",
        "name": "vin rouge de cuisine",
        "unit": "17c4cd83"
    },
    {
        "domain": "164a7427",
        "gid": "d553a4e6",
        "name": "feuilles de laurier",
        "unit": "590c07ad"
    },
    {
        "domain": "164a7427",
        "gid": "eca9b6d5",
        "name": "feuilles de basilic",
        "unit": "590c07ad"
    },
    {
        "domain": "17b14bbf",
        "gid": "95fdef58",
        "name": "muscade r\u00e2p\u00e9e",
        "unit": "ec7b99e0"
    },
    {
        "domain": "39b88b46",
        "gid": "d7df33bf",
        "name": "emmental fran\u00e7ais",
        "unit": "ffa29d26"
    },
    {
        "domain": "39b88b46",
        "gid": "eb76b90e",
        "name": "parmesan r\u00e2p\u00e9",
        "unit": "ffa29d26"
    },
    {
        "domain": "17b14bbf",
        "gid": "00738994",
        "name": "farine",
        "unit": "ffa29d26"
    },
    {
        "domain": "39b88b46",
        "gid": "155f3d75",
        "name": "beurre",
        "unit": "ffa29d26"
    },
    {
        "domain": "39b88b46",
        "gid": "0f6a3748",
        "name": "lait",
        "unit": "6429c27c"
    }
]